CHANGELOG.md
desktopspy/__init__.py
desktopspy/trackers.py
desktopspy-0.0.1.dist-info/LICENSE
desktopspy-0.0.1.dist-info/WHEEL
desktopspy-0.0.1.dist-info/METADATA
desktopspy-0.0.1.dist-info/RECORD
